<?xml version="1.0" encoding="UTF-8"?><oai_dc:dc xmlns:oai_dc="http://www.openarchives.org/OAI/2.0/oai_dc/" xmlns:dc="http://purl.org/dc/elements/1.1/" xmlns:xsi="http://www.w3.org/2001/XMLSchema-instance" xsi:schemaLocation="http://www.openarchives.org/OAI/2.0/oai_dc/ http://www.openarchives.org/OAI/2.0/oai_dc.xsd"><dc:identifier>http://zaguan.unizar.es/record/16308</dc:identifier><dc:language>spa</dc:language><dc:creator>Cruellas Villas, Javier</dc:creator><dc:creator>García Martín, Elena</dc:creator><dc:creator>Polo Llorens, Vicente</dc:creator><dc:title>Calidad visual en el glaucoma</dc:title><dc:description>Objetivo: Estudiar la calidad visual en el glaucoma primario de ángulo abierto y correlacionarlo con la progresión glaucomatosa.  Pacientes, material y métodos: Se estudiaron 38 ojos de 19 pacientes. Los siguientes test fueron realizados a cada paciente: agudeza visual ETDRs, Pelli Robson, CSV1000E, pupilometría, halometría, aberrometría y topografía (kr1w Topcon). Resultados: La edad promedio de los pacientes fue 66,125±9,83 años, 13 ojos (34%) presentaron glaucoma estadio 0, 8 ojos (21%) presentaron glaucoma estadio 1, 5 ojos (13%) presentaron glaucoma estadio 2, 3 ojos (8 %) presentaron glaucoma estadio 3, 3 ojos (8%) presentaron glaucoma estadio 4 y 6 ojos (16%) no fueron clasificados. La agudeza visual y la sensibilidad al contraste medida con el test Pelli Robson mostraron diferencias estadísticamente significativas (p&lt;0,05) entre los diferentes grados de glaucoma. La aberrometría mostró diferencias estadísticamente significativas (p&lt;0,05) entre los resultados de los otros test. Conclusión: la evaluación de la función visual es un valor útil en el seguimiento y diagnóstico precoz del glaucoma.</dc:description><dc:publisher>Universidad de Zaragoza</dc:publisher><dc:identifier>TAZ-TFG-2014-1652</dc:identifier><dc:identifier>oai:zaguan.unizar.es:16308</dc:identifier><dc:date>2014</dc:date></oai_dc:dc>